cybos_hj3415/__init__.py
cybos_hj3415/client.py
cybos_hj3415/client_tcp.py
cybos_hj3415/client_udp.py
cybos_hj3415/data.py
cybos_hj3415/setting.py
cybos_hj3415-0.2.7.dist-info/LICENSE
cybos_hj3415-0.2.7.dist-info/METADATA
cybos_hj3415-0.2.7.dist-info/WHEEL
cybos_hj3415-0.2.7.dist-info/top_level.txt
cybos_hj3415-0.2.7.dist-info/RECORD
