Metadata-Version: 2.1
Name: cybos-hj3415
Version: 0.2.7
Summary: Manage cybos program.
Home-page: https://pypi.org/project/cybos-hj3415/
Author: hyungjin kim
Author-email: hj3415@gmail.com
License: UNKNOWN
Project-URL: Bug Tracker, https://pypi.org/project/cybos-hj3415/
Platform: UNKNOWN
Classifier: Programming Language :: Python :: 3
Classifier: License :: OSI Approved :: MIT License
Classifier: Operating System :: OS Independent
Requires-Python: >=3.6
License-File: LICENSE
Requires-Dist: cybos-hj3415 (>=0.2.7)
Requires-Dist: util-hj3415 (>=0.2.10)
